spdx_checker/__init__.py
spdx_checker/__init__.pyi
spdx_checker/py.typed
spdx_checker/spdx_checker.abi3.so
spdx_checker-0.1.20.dist-info/METADATA
spdx_checker-0.1.20.dist-info/WHEEL
spdx_checker-0.1.20.dist-info/top_level.txt
spdx_checker-0.1.20.dist-info/RECORD
spdx_checker-0.1.20.dist-info/licenses/LICENSE
