Metadata-Version: 2.4
Name: spdx_checker
Version: 0.1.20
Summary: Fast SPDX License Checker for Source Code
Author: Tobias Stach
Requires-Python: >=3.11
License-File: LICENSE
Dynamic: license-file
Dynamic: requires-python
